gtp5_ej7_SIPO_reg/SIPOdesplReg_4bit.v
module SIPOdespReg_4bit (
    input wire clk,
    input wire D0,
    output reg [3:0] Q
);

//Internal variable declaration

//Body
always @(posedge clk) begin
    Q[3] = Q[2];
    Q[2] = Q[1];
    Q[1] = Q[0];
    Q[0] = D0;
end
            
endmodule

gtp5_ej7_SIPO_reg/SIPOdesplReg_4bit_tb.v
//-------------------------------------------------------------------
//-- SIPOdesplReg_4bit_tb.v
//-- Testbench
//-------------------------------------------------------------------
//-- Eberhardt Maximiliano
//-- GPL license
//-------------------------------------------------------------------

`default_nettype none
`define DUMPSTR(x) `"x.vcd`"
`timescale 100 ns / 10 ns
// timescale <time_unit> / <time_precision>

module SIPOdesplReg_4bit_tb();

//-- Simulation time: 1us (10 * 100ns)
parameter DURATION = 10;

//-- Clock signal. It is not used in this simulation
reg clk = 0;
always #0.5 clk = ~clk;

// SIPOdespReg_4bit ports
reg d0_test;
wire [3:0] q_test;

SIPOdespReg_4bit UUT(
    .clk(clk),
    .D0(d0_test),
    .Q(q_test)
);

integer i;

//Tip para probar TODAS las posibilidades de entrada posibles 
//always #10 {j,k} = 

initial begin

    //-- File were to store the simulation results
    $dumpfile(`DUMPSTR(`VCD_OUTPUT));
    $dumpvars(0, SIPOdesplReg_4bit_tb);

    for (i=0; i<16; i=i+1)
    begin
        $display ("Current loop # %0d", i);
        $display ("Current loop # %0b", i);

        #1
        d0_test = 0;

        #1
        d0_test = 1;

        #1
        d0_test = 0;

        #1
        d0_test = 1;
       
    end

    #(DURATION) $display("End of simulation");
    $finish;
end

endmodule

gtp5_ej7_SIPO_reg/SIPOdesplReg_4bit_tb.vcd
$date
	Wed May 15 23:19:48 2024
$end
$version
	Icarus Verilog
$end
$timescale
	1ps
$end
$scope module SIPOdesplReg_4bit_tb $end
$var wire 4 ! q_test [3:0] $end
$var reg 1 " clk $end
$var reg 1 # d0_test $end
$var integer 32 $ i [31:0] $end
$scope module UUT $end
$var wire 1 # D0 $end
$var wire 1 " clk $end
$var reg 4 % Q [3:0] $end
$upscope $end
$upscope $end
$enddefinitions $end
#0
$dumpvars
bx %
b0 $
x#
0"
bx !
$end
#50000
1"
#100000
0"
0#
#150000
bx0 !
bx0 %
1"
#200000
0"
1#
#250000
bx01 !
bx01 %
1"
#300000
0"
0#
#350000
bx010 !
bx010 %
1"
#400000
0"
b1 $
1#
#450000
b101 !
b101 %
1"
#500000
0"
0#
#550000
b1010 !
b1010 %
1"
#600000
0"
1#
#650000
b101 !
b101 %
1"
#700000
0"
0#
#750000
b1010 !
b1010 %
1"
#800000
0"
b10 $
1#
#850000
b101 !
b101 %
1"
#900000
0"
0#
#950000
b1010 !
b1010 %
1"
#1000000
0"
1#
#1050000
b101 !
b101 %
1"
#1100000
0"
0#
#1150000
b1010 !
b1010 %
1"
#1200000
0"
b11 $
1#
#1250000
b101 !
b101 %
1"
#1300000
0"
0#
#1350000
b1010 !
b1010 %
1"
#1400000
0"
1#
#1450000
b101 !
b101 %
1"
#1500000
0"
0#
#1550000
b1010 !
b1010 %
1"
#1600000
0"
b100 $
1#
#1650000
b101 !
b101 %
1"
#1700000
0"
0#
#1750000
b1010 !
b1010 %
1"
#1800000
0"
1#
#1850000
b101 !
b101 %
1"
#1900000
0"
0#
#1950000
b1010 !
b1010 %
1"
#2000000
0"
b101 $
1#
#2050000
b101 !
b101 %
1"
#2100000
0"
0#
#2150000
b1010 !
b1010 %
1"
#2200000
0"
1#
#2250000
b101 !
b101 %
1"
#2300000
0"
0#
#2350000
b1010 !
b1010 %
1"
#2400000
0"
b110 $
1#
#2450000
b101 !
b101 %
1"
#2500000
0"
0#
#2550000
b1010 !
b1010 %
1"
#2600000
0"
1#
#2650000
b101 !
b101 %
1"
#2700000
0"
0#
#2750000
b1010 !
b1010 %
1"
#2800000
0"
b111 $
1#
#2850000
b101 !
b101 %
1"
#2900000
0"
0#
#2950000
b1010 !
b1010 %
1"
#3000000
0"
1#
#3050000
b101 !
b101 %
1"
#3100000
0"
0#
#3150000
b1010 !
b1010 %
1"
#3200000
0"
b1000 $
1#
#3250000
b101 !
b101 %
1"
#3300000
0"
0#
#3350000
b1010 !
b1010 %
1"
#3400000
0"
1#
#3450000
b101 !
b101 %
1"
#3500000
0"
0#
#3550000
b1010 !
b1010 %
1"
#3600000
0"
b1001 $
1#
#3650000
b101 !
b101 %
1"
#3700000
0"
0#
#3750000
b1010 !
b1010 %
1"
#3800000
0"
1#
#3850000
b101 !
b101 %
1"
#3900000
0"
0#
#3950000
b1010 !
b1010 %
1"
#4000000
0"
b1010 $
1#
#4050000
b101 !
b101 %
1"
#4100000
0"
0#
#4150000
b1010 !
b1010 %
1"
#4200000
0"
1#
#4250000
b101 !
b101 %
1"
#4300000
0"
0#
#4350000
b1010 !
b1010 %
1"
#4400000
0"
b1011 $
1#
#4450000
b101 !
b101 %
1"
#4500000
0"
0#
#4550000
b1010 !
b1010 %
1"
#4600000
0"
1#
#4650000
b101 !
b101 %
1"
#4700000
0"
0#
#4750000
b1010 !
b1010 %
1"
#4800000
0"
b1100 $
1#
#4850000
b101 !
b101 %
1"
#4900000
0"
0#
#4950000
b1010 !
b1010 %
1"
#5000000
0"
1#
#5050000
b101 !
b101 %
1"
#5100000
0"
0#
#5150000
b1010 !
b1010 %
1"
#5200000
0"
b1101 $
1#
#5250000
b101 !
b101 %
1"
#5300000
0"
0#
#5350000
b1010 !
b1010 %
1"
#5400000
0"
1#
#5450000
b101 !
b101 %
1"
#5500000
0"
0#
#5550000
b1010 !
b1010 %
1"
#5600000
0"
b1110 $
1#
#5650000
b101 !
b101 %
1"
#5700000
0"
0#
#5750000
b1010 !
b1010 %
1"
#5800000
0"
1#
#5850000
b101 !
b101 %
1"
#5900000
0"
0#
#5950000
b1010 !
b1010 %
1"
#6000000
0"
b1111 $
1#
#6050000
b101 !
b101 %
1"
#6100000
0"
0#
#6150000
b1010 !
b1010 %
1"
#6200000
0"
1#
#6250000
b101 !
b101 %
1"
#6300000
0"
0#
#6350000
b1010 !
b1010 %
1"
#6400000
0"
b10000 $
1#
#6450000
b101 !
b101 %
1"
#6500000
0"
#6550000
b1011 !
b1011 %
1"
#6600000
0"
#6650000
b111 !
b111 %
1"
#6700000
0"
#6750000
b1111 !
b1111 %
1"
