gtp5_ej6_4bitReg/4bitRegister.v
module PIPOreg_4bits (
    input wire clk, load,
    input wire [3:0] data,
    output reg [3:0] Q
);

//Internal variable declaration

//Implementacion usada en la que se resuelve todo en un solo modulo sin hacer instancia de otros modulos.
//Body
always @(posedge clk, posedge load) begin
    if (load) begin
        Q[3] = data[3];
        Q[2] = data[2];
        Q[1] = data[1];
        Q[0] = data[0];
    end
    else begin
        Q[3] = Q[3];
        Q[2] = Q[2];
        Q[1] = Q[1];
        Q[0] = Q[0];
    end
end

endmodule

gtp5_ej6_4bitReg/4bitRegister_tb.v
//-------------------------------------------------------------------
//-- 4bitRegister_tb.v
//-- Testbench
//-------------------------------------------------------------------
//-- Eberhardt Maximiliano
//-- GPL license
//-------------------------------------------------------------------

`default_nettype none
`define DUMPSTR(x) `"x.vcd`"
`timescale 100 ns / 10 ns
// timescale <time_unit> / <time_precision>

module PIPOreg_4bits_tb();

//-- Simulation time: 1us (10 * 100ns)
parameter DURATION = 10;

//-- Clock signal. It is not used in this simulation
reg clk = 0;
always #0.5 clk = ~clk;

// 4bitPIPOreg ports
reg [3:0] data_test;
reg load_test;
wire [3:0] q_test;

PIPOreg_4bits UUT(
    .clk(clk),
    .load(load_test),
    .data(data_test),
    .Q(q_test)
);

integer i;

//Tip para probar TODAS las posibilidades de entrada posibles 
//always #10 {j,k} = 

initial begin

    //-- File were to store the simulation results
    $dumpfile(`DUMPSTR(`VCD_OUTPUT));
    $dumpvars(0, PIPOreg_4bits_tb);

    for (i=0; i<16; i=i+1)
    begin
        $display ("Current loop # %0d", i);
        $display ("Current loop # %0b", i);

        data_test = 4'b1010;
        load_test = 0;

        #2
        load_test = 1;

        #2
        data_test = 4'b0101;
        load_test = 0;

        #2
        data_test = 4'b0101;
        load_test = 1;

    end

    #(DURATION) $display("End of simulation");
    $finish;
end

endmodule

gtp5_ej6_4bitReg/4bitRegister_tb.vcd
$date
	Wed May 15 21:52:33 2024
$end
$version
	Icarus Verilog
$end
$timescale
	1ps
$end
$scope module PIPOreg_4bits_tb $end
$var wire 4 ! q_test [3:0] $end
$var reg 1 " clk $end
$var reg 4 # data_test [3:0] $end
$var reg 1 $ load_test $end
$var integer 32 % i [31:0] $end
$scope module UUT $end
$var wire 1 " clk $end
$var wire 4 & data [3:0] $end
$var wire 1 $ load $end
$var reg 4 ' Q [3:0] $end
$upscope $end
$upscope $end
$enddefinitions $end
#0
$dumpvars
bx '
b1010 &
b0 %
0$
b1010 #
0"
bx !
$end
#50000
1"
#100000
0"
#150000
1"
#200000
b1010 !
b1010 '
0"
1$
#250000
1"
#300000
0"
#350000
1"
#400000
0"
0$
b101 #
b101 &
#450000
1"
#500000
0"
#550000
1"
#600000
0"
b1010 #
b1010 &
b1 %
0$
#650000
1"
#700000
0"
#750000
1"
#800000
0"
1$
#850000
1"
#900000
0"
#950000
1"
#1000000
0"
0$
b101 #
b101 &
#1050000
1"
#1100000
0"
#1150000
1"
#1200000
0"
b1010 #
b1010 &
b10 %
0$
#1250000
1"
#1300000
0"
#1350000
1"
#1400000
0"
1$
#1450000
1"
#1500000
0"
#1550000
1"
#1600000
0"
0$
b101 #
b101 &
#1650000
1"
#1700000
0"
#1750000
1"
#1800000
0"
b1010 #
b1010 &
b11 %
0$
#1850000
1"
#1900000
0"
#1950000
1"
#2000000
0"
1$
#2050000
1"
#2100000
0"
#2150000
1"
#2200000
0"
0$
b101 #
b101 &
#2250000
1"
#2300000
0"
#2350000
1"
#2400000
0"
b1010 #
b1010 &
b100 %
0$
#2450000
1"
#2500000
0"
#2550000
1"
#2600000
0"
1$
#2650000
1"
#2700000
0"
#2750000
1"
#2800000
0"
0$
b101 #
b101 &
#2850000
1"
#2900000
0"
#2950000
1"
#3000000
0"
b1010 #
b1010 &
b101 %
0$
#3050000
1"
#3100000
0"
#3150000
1"
#3200000
0"
1$
#3250000
1"
#3300000
0"
#3350000
1"
#3400000
0"
0$
b101 #
b101 &
#3450000
1"
#3500000
0"
#3550000
1"
#3600000
0"
b1010 #
b1010 &
b110 %
0$
#3650000
1"
#3700000
0"
#3750000
1"
#3800000
0"
1$
#3850000
1"
#3900000
0"
#3950000
1"
#4000000
0"
0$
b101 #
b101 &
#4050000
1"
#4100000
0"
#4150000
1"
#4200000
0"
b1010 #
b1010 &
b111 %
0$
#4250000
1"
#4300000
0"
#4350000
1"
#4400000
0"
1$
#4450000
1"
#4500000
0"
#4550000
1"
#4600000
0"
0$
b101 #
b101 &
#4650000
1"
#4700000
0"
#4750000
1"
#4800000
0"
b1010 #
b1010 &
b1000 %
0$
#4850000
1"
#4900000
0"
#4950000
1"
#5000000
0"
1$
#5050000
1"
#5100000
0"
#5150000
1"
#5200000
0"
0$
b101 #
b101 &
#5250000
1"
#5300000
0"
#5350000
1"
#5400000
0"
b1010 #
b1010 &
b1001 %
0$
#5450000
1"
#5500000
0"
#5550000
1"
#5600000
0"
1$
#5650000
1"
#5700000
0"
#5750000
1"
#5800000
0"
0$
b101 #
b101 &
#5850000
1"
#5900000
0"
#5950000
1"
#6000000
0"
b1010 #
b1010 &
b1010 %
0$
#6050000
1"
#6100000
0"
#6150000
1"
#6200000
0"
1$
#6250000
1"
#6300000
0"
#6350000
1"
#6400000
0"
0$
b101 #
b101 &
#6450000
1"
#6500000
0"
#6550000
1"
#6600000
0"
b1010 #
b1010 &
b1011 %
0$
#6650000
1"
#6700000
0"
#6750000
1"
#6800000
0"
1$
#6850000
1"
#6900000
0"
#6950000
1"
#7000000
0"
0$
b101 #
b101 &
#7050000
1"
#7100000
0"
#7150000
1"
#7200000
0"
b1010 #
b1010 &
b1100 %
0$
#7250000
1"
#7300000
0"
#7350000
1"
#7400000
0"
1$
#7450000
1"
#7500000
0"
#7550000
1"
#7600000
0"
0$
b101 #
b101 &
#7650000
1"
#7700000
0"
#7750000
1"
#7800000
0"
b1010 #
b1010 &
b1101 %
0$
#7850000
1"
#7900000
0"
#7950000
1"
#8000000
0"
1$
#8050000
1"
#8100000
0"
#8150000
1"
#8200000
0"
0$
b101 #
b101 &
#8250000
1"
#8300000
0"
#8350000
1"
#8400000
0"
b1010 #
b1010 &
b1110 %
0$
#8450000
1"
#8500000
0"
#8550000
1"
#8600000
0"
1$
#8650000
1"
#8700000
0"
#8750000
1"
#8800000
0"
0$
b101 #
b101 &
#8850000
1"
#8900000
0"
#8950000
1"
#9000000
0"
b1010 #
b1010 &
b1111 %
0$
#9050000
1"
#9100000
0"
#9150000
1"
#9200000
0"
1$
#9250000
1"
#9300000
0"
#9350000
1"
#9400000
0"
0$
b101 #
b101 &
#9450000
1"
#9500000
0"
#9550000
1"
#9600000
b101 !
b101 '
0"
b10000 %
1$
