gtp5_ej8_SISObidirec/SISObidi_4bit.v
module SISObidi_4bit (
    input wire clk, rst,
    input wire I_D,
    input wire Data,
    output reg Salida
);

//Internal variable declaration 
reg [3:0] register = 4'b0000; //Registro interno que representa los 4FF

//Body
always @(posedge rst) begin
    if (rst) begin
        register = 4'b0000;
    end
end

always @(posedge clk, posedge rst) begin
    /*if (rst) begin
        register = 4'b0000;
    end*/

    if (I_D) begin
        register[0] <= Data;
        register[1] <= register[0];
        register[2] <= register[1];
        register[3] <= register[2];
        Salida <= register[3];
    end
    else begin
        register[3] <= Data;
        register[2] <= register[3];
        register[1] <= register[2];
        register[0] <= register[1];
        Salida <= register[0];
    end

end
    
endmodule

gtp5_ej8_SISObidirec/SISObidi_4bit_tb.v
//-------------------------------------------------------------------
//-- SISObidi_4bit_tb.v
//-- Testbench
//-------------------------------------------------------------------
//-- Eberhardt Maximiliano
//-- GPL license
//-------------------------------------------------------------------

`default_nettype none
`define DUMPSTR(x) `"x.vcd`"
`timescale 100 ns / 10 ns
// timescale <time_unit> / <time_precision>

module SISObidi_4bit_tb();

//-- Simulation time: 1us (10 * 100ns)
parameter DURATION = 10;

//-- Clock signal. It is not used in this simulation
reg clk = 0;
always #0.5 clk = ~clk;

// SISObidi_4bit ports
reg rst_test, i_d_test, d_test;
wire q_test;

SISObidi_4bit UUT(
    .clk(clk),
    .rst(rst_test),
    .I_D(i_d_test),
    .Data(d_test),
    .Salida(q_test)
);

integer i;

//Tip para probar TODAS las posibilidades de entrada posibles 
//always #10 {j,k} = 

initial begin

    //-- File were to store the simulation results
    $dumpfile(`DUMPSTR(`VCD_OUTPUT));
    $dumpvars(0, SISObidi_4bit_tb);

    for (i=0; i<16; i=i+1)
    begin
        $display ("Current loop # %0d", i);
        $display ("Current loop # %0b", i);

        #1
        rst_test = 0;
        i_d_test = 1;
        d_test = 1;
        
        #1
        d_test = 0;

        #1
        d_test = 0;

        #1
        d_test = 0;

        #1
        d_test = 1;

        #1
        rst_test = 1;

        #1
        rst_test = 0;
        d_test = 0;

        #1
        d_test = 0;

        #1
        d_test = 1;

        #1
        i_d_test = 0;
        d_test = 0;

        #1
        d_test = 1;
       
    end

    #(DURATION) $display("End of simulation");
    $finish;
end

endmodule

gtp5_ej8_SISObidirec/SISObidi_4bit_tb.vcd
$date
	Wed May 22 18:42:50 2024
$end
$version
	Icarus Verilog
$end
$timescale
	1ps
$end
$scope module SISObidi_4bit_tb $end
$var wire 1 ! q_test $end
$var reg 1 " clk $end
$var reg 1 # d_test $end
$var reg 1 $ i_d_test $end
$var reg 1 % rst_test $end
$var integer 32 & i [31:0] $end
$scope module UUT $end
$var wire 1 # Data $end
$var wire 1 $ I_D $end
$var wire 1 " clk $end
$var wire 1 % rst $end
$var reg 1 ! Salida $end
$var reg 4 ' register [3:0] $end
$upscope $end
$upscope $end
$enddefinitions $end
#0
$dumpvars
b0 '
b0 &
x%
x$
x#
0"
x!
$end
#50000
0!
bx000 '
1"
#100000
0"
1#
1$
0%
#150000
x!
b1 '
1"
#200000
0"
0#
#250000
0!
b10 '
1"
#300000
0"
#350000
b100 '
1"
#400000
0"
#450000
b1000 '
1"
#500000
0"
1#
#550000
1!
b1 '
1"
#600000
0!
b1 '
0"
1%
#650000
b11 '
1"
#700000
0"
0#
0%
#750000
b110 '
1"
#800000
0"
#850000
b1100 '
1"
#900000
0"
1#
#950000
1!
b1001 '
1"
#1000000
0"
0#
0$
#1050000
b100 '
1"
#1100000
0"
b1 &
1#
#1150000
0!
b1010 '
1"
#1200000
0"
1$
#1250000
1!
b101 '
1"
#1300000
0"
0#
#1350000
0!
b1010 '
1"
#1400000
0"
#1450000
1!
b100 '
1"
#1500000
0"
#1550000
0!
b1000 '
1"
#1600000
0"
1#
#1650000
1!
b1 '
1"
#1700000
0!
b1 '
0"
1%
#1750000
b11 '
1"
#1800000
0"
0#
0%
#1850000
b110 '
1"
#1900000
0"
#1950000
b1100 '
1"
#2000000
0"
1#
#2050000
1!
b1001 '
1"
#2100000
0"
0#
0$
#2150000
b100 '
1"
#2200000
0"
b10 &
1#
#2250000
0!
b1010 '
1"
#2300000
0"
1$
#2350000
1!
b101 '
1"
#2400000
0"
0#
#2450000
0!
b1010 '
1"
#2500000
0"
#2550000
1!
b100 '
1"
#2600000
0"
#2650000
0!
b1000 '
1"
#2700000
0"
1#
#2750000
1!
b1 '
1"
#2800000
0!
b1 '
0"
1%
#2850000
b11 '
1"
#2900000
0"
0#
0%
#2950000
b110 '
1"
#3000000
0"
#3050000
b1100 '
1"
#3100000
0"
1#
#3150000
1!
b1001 '
1"
#3200000
0"
0#
0$
#3250000
b100 '
1"
#3300000
0"
b11 &
1#
#3350000
0!
b1010 '
1"
#3400000
0"
1$
#3450000
1!
b101 '
1"
#3500000
0"
0#
#3550000
0!
b1010 '
1"
#3600000
0"
#3650000
1!
b100 '
1"
#3700000
0"
#3750000
0!
b1000 '
1"
#3800000
0"
1#
#3850000
1!
b1 '
1"
#3900000
0!
b1 '
0"
1%
#3950000
b11 '
1"
#4000000
0"
0#
0%
#4050000
b110 '
1"
#4100000
0"
#4150000
b1100 '
1"
#4200000
0"
1#
#4250000
1!
b1001 '
1"
#4300000
0"
0#
0$
#4350000
b100 '
1"
#4400000
0"
b100 &
1#
#4450000
0!
b1010 '
1"
#4500000
0"
1$
#4550000
1!
b101 '
1"
#4600000
0"
0#
#4650000
0!
b1010 '
1"
#4700000
0"
#4750000
1!
b100 '
1"
#4800000
0"
#4850000
0!
b1000 '
1"
#4900000
0"
1#
#4950000
1!
b1 '
1"
#5000000
0!
b1 '
0"
1%
#5050000
b11 '
1"
#5100000
0"
0#
0%
#5150000
b110 '
1"
#5200000
0"
#5250000
b1100 '
1"
#5300000
0"
1#
#5350000
1!
b1001 '
1"
#5400000
0"
0#
0$
#5450000
b100 '
1"
#5500000
0"
b101 &
1#
#5550000
0!
b1010 '
1"
#5600000
0"
1$
#5650000
1!
b101 '
1"
#5700000
0"
0#
#5750000
0!
b1010 '
1"
#5800000
0"
#5850000
1!
b100 '
1"
#5900000
0"
#5950000
0!
b1000 '
1"
#6000000
0"
1#
#6050000
1!
b1 '
1"
#6100000
0!
b1 '
0"
1%
#6150000
b11 '
1"
#6200000
0"
0#
0%
#6250000
b110 '
1"
#6300000
0"
#6350000
b1100 '
1"
#6400000
0"
1#
#6450000
1!
b1001 '
1"
#6500000
0"
0#
0$
#6550000
b100 '
1"
#6600000
0"
b110 &
1#
#6650000
0!
b1010 '
1"
#6700000
0"
1$
#6750000
1!
b101 '
1"
#6800000
0"
0#
#6850000
0!
b1010 '
1"
#6900000
0"
#6950000
1!
b100 '
1"
#7000000
0"
#7050000
0!
b1000 '
1"
#7100000
0"
1#
#7150000
1!
b1 '
1"
#7200000
0!
b1 '
0"
1%
#7250000
b11 '
1"
#7300000
0"
0#
0%
#7350000
b110 '
1"
#7400000
0"
#7450000
b1100 '
1"
#7500000
0"
1#
#7550000
1!
b1001 '
1"
#7600000
0"
0#
0$
#7650000
b100 '
1"
#7700000
0"
b111 &
1#
#7750000
0!
b1010 '
1"
#7800000
0"
1$
#7850000
1!
b101 '
1"
#7900000
0"
0#
#7950000
0!
b1010 '
1"
#8000000
0"
#8050000
1!
b100 '
1"
#8100000
0"
#8150000
0!
b1000 '
1"
#8200000
0"
1#
#8250000
1!
b1 '
1"
#8300000
0!
b1 '
0"
1%
#8350000
b11 '
1"
#8400000
0"
0#
0%
#8450000
b110 '
1"
#8500000
0"
#8550000
b1100 '
1"
#8600000
0"
1#
#8650000
1!
b1001 '
1"
#8700000
0"
0#
0$
#8750000
b100 '
1"
#8800000
0"
b1000 &
1#
#8850000
0!
b1010 '
1"
#8900000
0"
1$
#8950000
1!
b101 '
1"
#9000000
0"
0#
#9050000
0!
b1010 '
1"
#9100000
0"
#9150000
1!
b100 '
1"
#9200000
0"
#9250000
0!
b1000 '
1"
#9300000
0"
1#
#9350000
1!
b1 '
1"
#9400000
0!
b1 '
0"
1%
#9450000
b11 '
1"
#9500000
0"
0#
0%
#9550000
b110 '
1"
#9600000
0"
#9650000
b1100 '
1"
#9700000
0"
1#
#9750000
1!
b1001 '
1"
#9800000
0"
0#
0$
#9850000
b100 '
1"
#9900000
0"
b1001 &
1#
#9950000
0!
b1010 '
1"
#10000000
0"
1$
#10050000
1!
b101 '
1"
#10100000
0"
0#
#10150000
0!
b1010 '
1"
#10200000
0"
#10250000
1!
b100 '
1"
#10300000
0"
#10350000
0!
b1000 '
1"
#10400000
0"
1#
#10450000
1!
b1 '
1"
#10500000
0!
b1 '
0"
1%
#10550000
b11 '
1"
#10600000
0"
0#
0%
#10650000
b110 '
1"
#10700000
0"
#10750000
b1100 '
1"
#10800000
0"
1#
#10850000
1!
b1001 '
1"
#10900000
0"
0#
0$
#10950000
b100 '
1"
#11000000
0"
b1010 &
1#
#11050000
0!
b1010 '
1"
#11100000
0"
1$
#11150000
1!
b101 '
1"
#11200000
0"
0#
#11250000
0!
b1010 '
1"
#11300000
0"
#11350000
1!
b100 '
1"
#11400000
0"
#11450000
0!
b1000 '
1"
#11500000
0"
1#
#11550000
1!
b1 '
1"
#11600000
0!
b1 '
0"
1%
#11650000
b11 '
1"
#11700000
0"
0#
0%
#11750000
b110 '
1"
#11800000
0"
#11850000
b1100 '
1"
#11900000
0"
1#
#11950000
1!
b1001 '
1"
#12000000
0"
0#
0$
#12050000
b100 '
1"
#12100000
0"
b1011 &
1#
#12150000
0!
b1010 '
1"
#12200000
0"
1$
#12250000
1!
b101 '
1"
#12300000
0"
0#
#12350000
0!
b1010 '
1"
#12400000
0"
#12450000
1!
b100 '
1"
#12500000
0"
#12550000
0!
b1000 '
1"
#12600000
0"
1#
#12650000
1!
b1 '
1"
#12700000
0!
b1 '
0"
1%
#12750000
b11 '
1"
#12800000
0"
0#
0%
#12850000
b110 '
1"
#12900000
0"
#12950000
b1100 '
1"
#13000000
0"
1#
#13050000
1!
b1001 '
1"
#13100000
0"
0#
0$
#13150000
b100 '
1"
#13200000
0"
b1100 &
1#
#13250000
0!
b1010 '
1"
#13300000
0"
1$
#13350000
1!
b101 '
1"
#13400000
0"
0#
#13450000
0!
b1010 '
1"
#13500000
0"
#13550000
1!
b100 '
1"
#13600000
0"
#13650000
0!
b1000 '
1"
#13700000
0"
1#
#13750000
1!
b1 '
1"
#13800000
0!
b1 '
0"
1%
#13850000
b11 '
1"
#13900000
0"
0#
0%
#13950000
b110 '
1"
#14000000
0"
#14050000
b1100 '
1"
#14100000
0"
1#
#14150000
1!
b1001 '
1"
#14200000
0"
0#
0$
#14250000
b100 '
1"
#14300000
0"
b1101 &
1#
#14350000
0!
b1010 '
1"
#14400000
0"
1$
#14450000
1!
b101 '
1"
#14500000
0"
0#
#14550000
0!
b1010 '
1"
#14600000
0"
#14650000
1!
b100 '
1"
#14700000
0"
#14750000
0!
b1000 '
1"
#14800000
0"
1#
#14850000
1!
b1 '
1"
#14900000
0!
b1 '
0"
1%
#14950000
b11 '
1"
#15000000
0"
0#
0%
#15050000
b110 '
1"
#15100000
0"
#15150000
b1100 '
1"
#15200000
0"
1#
#15250000
1!
b1001 '
1"
#15300000
0"
0#
0$
#15350000
b100 '
1"
#15400000
0"
b1110 &
1#
#15450000
0!
b1010 '
1"
#15500000
0"
1$
#15550000
1!
b101 '
1"
#15600000
0"
0#
#15650000
0!
b1010 '
1"
#15700000
0"
#15750000
1!
b100 '
1"
#15800000
0"
#15850000
0!
b1000 '
1"
#15900000
0"
1#
#15950000
1!
b1 '
1"
#16000000
0!
b1 '
0"
1%
#16050000
b11 '
1"
#16100000
0"
0#
0%
#16150000
b110 '
1"
#16200000
0"
#16250000
b1100 '
1"
#16300000
0"
1#
#16350000
1!
b1001 '
1"
#16400000
0"
0#
0$
#16450000
b100 '
1"
#16500000
0"
b1111 &
1#
#16550000
0!
b1010 '
1"
#16600000
0"
1$
#16650000
1!
b101 '
1"
#16700000
0"
0#
#16750000
0!
b1010 '
1"
#16800000
0"
#16850000
1!
b100 '
1"
#16900000
0"
#16950000
0!
b1000 '
1"
#17000000
0"
1#
#17050000
1!
b1 '
1"
#17100000
0!
b1 '
0"
1%
#17150000
b11 '
1"
#17200000
0"
0#
0%
#17250000
b110 '
1"
#17300000
0"
#17350000
b1100 '
1"
#17400000
0"
1#
#17450000
1!
b1001 '
1"
#17500000
0"
0#
0$
#17550000
b100 '
1"
#17600000
0"
b10000 &
1#
#17650000
0!
b1010 '
1"
#17700000
0"
#17750000
b1101 '
1"
#17800000
0"
#17850000
1!
b1110 '
1"
#17900000
0"
#17950000
0!
b1111 '
1"
#18000000
0"
#18050000
1!
1"
