gtp5_ej12_RAM/ram.v
module ram16words 
// Parameters
# 
(
parameter b = 4, // words size
          N = 4 // number of registers or addresses 

)

// Ports declarations
(
    input wire clk,
    input wire we, //WriteEnable
    input wire [N-1:0] address,
    input wire [b-1:0] write_data,
    output reg [b-1:0] read_data
);

//Declaracion de contenido de la RAM - Esto es como una matriz
reg [b-1:0] memory [0:N-1]; // En este caso seria una RAM de 16 direcciones en donde se pueden almacenar una palabra de 4 bits 

// 16 palabras de 4 bits cada una => 16 x 4 = 64 bits => 8 Bytes (small)

//Proceso de escritura de la RAM
always @(posedge clk) begin
    if (we) begin //Verifico que wrienable este activo
        memory[address] <= write_data; //Escribe los datos en la direccion
    end
end

//Proceso de lectura de la RAM
//No es necesario que sea sincronico
always @(*) begin
    //
    read_data <= memory[address]; //Lee datos en la direccion indicada
end
    
endmodule

//OJO QUE HAY MUCHA DATA IMPORTANTE PARA ENTENDER EL TEMA EN LAS DIAPOS DE GIOVANINI
//Tema Circuitos Secuenciales

gtp5_ej12_RAM/ram_tb.v
//-------------------------------------------------------------------
//-- ram_tb.v
//-- Testbench
//-------------------------------------------------------------------
//-- Eberhardt Maximiliano
//-- GPL license
//-------------------------------------------------------------------

`default_nettype none
`define DUMPSTR(x) `"x.vcd`"
`timescale 100 ns / 10 ns
// timescale <time_unit> / <time_precision>

module ram_tb();

//-- Simulation time: 1us (10 * 100ns)
parameter DURATION = 10;

//-- Clock signal. It is not used in this simulation
reg clk = 0;
always #0.5 clk = ~clk;

// ram ports
reg wr_en_test;
reg [3:0] address_test;
reg [3:0] d_test;
wire [3:0] q_test;

ram16words UUT(
    .clk(clk),
    .we(wr_en_test),
    .address(address_test),
    .write_data(d_test),
    .read_data(q_test)
);

integer i;

//Tip para probar TODAS las posibilidades de entrada posibles 
//always #10 {j,k} = 

initial begin

    //-- File were to store the simulation results
    $dumpfile(`DUMPSTR(`VCD_OUTPUT));
    $dumpvars(0, ram_tb);

    //for (i=0; i<16; i=i+1)
    begin
        $display ("Current loop # %0d", i);
        $display ("Current loop # %0b", i);

        // Initialize signals
        clk = 0;
        wr_en_test = 0;
        address_test = 4'b0000;
        d_test = 4'b0000;
        
        // Wait for global reset
        #10;
        
        // Test case 1: Write and read from address 0
        wr_en_test = 1;
        address_test = 4'b0000;
        d_test = 4'b1010;
        #10;
        wr_en_test = 0;
        #10;
        if (q_test != 4'b1010) $display("Test case 1 failed");
        
        // Test case 2: Write and read from address 1
        wr_en_test = 1;
        address_test = 4'b0001;
        d_test = 4'b1100;
        #10;
        wr_en_test = 0;
        #10;
        if (q_test != 4'b1100) $display("Test case 2 failed");
        
        // Test case 3: Write and read from address 15
        wr_en_test = 1;
        address_test = 4'b1111;
        d_test = 4'b1111;
        #10;
        wr_en_test = 0;
        #10;
        if (q_test != 4'b1111) $display("Test case 3 failed");
        
        // Additional test cases can be added here
        wr_en_test = 1;
        address_test = 4'b0010;
        d_test = 4'b1011;
        

    end

    #(DURATION) $display("End of simulation");
    $finish;
end

endmodule

gtp5_ej12_RAM/ram_tb.vcd
$date
	Wed May 29 22:50:39 2024
$end
$version
	Icarus Verilog
$end
$timescale
	1ps
$end
$scope module ram_tb $end
$var wire 4 ! q_test [3:0] $end
$var reg 4 " address_test [3:0] $end
$var reg 1 # clk $end
$var reg 4 $ d_test [3:0] $end
$var reg 1 % wr_en_test $end
$var integer 32 & i [31:0] $end
$scope module UUT $end
$var wire 4 ' address [3:0] $end
$var wire 1 # clk $end
$var wire 1 % we $end
$var wire 4 ( write_data [3:0] $end
$var reg 4 ) read_data [3:0] $end
$upscope $end
$upscope $end
$enddefinitions $end
#0
$dumpvars
bx )
b0 (
b0 '
bx &
0%
b0 $
0#
b0 "
bx !
$end
#50000
1#
#100000
0#
#150000
1#
#200000
0#
#250000
1#
#300000
0#
#350000
1#
#400000
0#
#450000
1#
#500000
0#
#550000
1#
#600000
0#
#650000
1#
#700000
0#
#750000
1#
#800000
0#
#850000
1#
#900000
0#
#950000
1#
#1000000
0#
b1010 $
b1010 (
1%
#1050000
b1010 !
b1010 )
1#
#1100000
0#
#1150000
1#
#1200000
0#
#1250000
1#
#1300000
0#
#1350000
1#
#1400000
0#
#1450000
1#
#1500000
0#
#1550000
1#
#1600000
0#
#1650000
1#
#1700000
0#
#1750000
1#
#1800000
0#
#1850000
1#
#1900000
0#
#1950000
1#
#2000000
0#
0%
#2050000
1#
#2100000
0#
#2150000
1#
#2200000
0#
#2250000
1#
#2300000
0#
#2350000
1#
#2400000
0#
#2450000
1#
#2500000
0#
#2550000
1#
#2600000
0#
#2650000
1#
#2700000
0#
#2750000
1#
#2800000
0#
#2850000
1#
#2900000
0#
#2950000
1#
#3000000
bx !
bx )
0#
b1100 $
b1100 (
b1 "
b1 '
1%
#3050000
b1100 !
b1100 )
1#
#3100000
0#
#3150000
1#
#3200000
0#
#3250000
1#
#3300000
0#
#3350000
1#
#3400000
0#
#3450000
1#
#3500000
0#
#3550000
1#
#3600000
0#
#3650000
1#
#3700000
0#
#3750000
1#
#3800000
0#
#3850000
1#
#3900000
0#
#3950000
1#
#4000000
0#
0%
#4050000
1#
#4100000
0#
#4150000
1#
#4200000
0#
#4250000
1#
#4300000
0#
#4350000
1#
#4400000
0#
#4450000
1#
#4500000
0#
#4550000
1#
#4600000
0#
#4650000
1#
#4700000
0#
#4750000
1#
#4800000
0#
#4850000
1#
#4900000
0#
#4950000
1#
#5000000
bx !
bx )
0#
b1111 $
b1111 (
b1111 "
b1111 '
1%
#5050000
b1111 !
b1111 )
1#
#5100000
0#
#5150000
1#
#5200000
0#
#5250000
1#
#5300000
0#
#5350000
1#
#5400000
0#
#5450000
1#
#5500000
0#
#5550000
1#
#5600000
0#
#5650000
1#
#5700000
0#
#5750000
1#
#5800000
0#
#5850000
1#
#5900000
0#
#5950000
1#
#6000000
0#
0%
#6050000
1#
#6100000
0#
#6150000
1#
#6200000
0#
#6250000
1#
#6300000
0#
#6350000
1#
#6400000
0#
#6450000
1#
#6500000
0#
#6550000
1#
#6600000
0#
#6650000
1#
#6700000
0#
#6750000
1#
#6800000
0#
#6850000
1#
#6900000
0#
#6950000
1#
#7000000
bx !
bx )
0#
b1011 $
b1011 (
b10 "
b10 '
1%
#7050000
b1011 !
b1011 )
1#
