TPI_CajaMusicalFinal/freqdividerM/freqdividerM.v
module freqdividerM(
    input wire clk,
    output wire clk_salida
);
    
//-- Valor por defecto del divisor , nosotros se lo vamos a tener que pasar por entrada
parameter M = 45801; // Valor de prueba para nota Do
    
//-- Numero de bits para almacenar el divisor
//-- Se calculan con la funcion de verilog $clog2, que nos devuelve el 
//-- numero de bits necesarios para representar el numero M

//-- Es un parametro local, que no se puede modificar al instanciar
localparam N = $clog2(M);
    
//-- Registro para implementar el contador modulo M
reg [N-1:0] contadorParaDividir = 0;
    
//-- Contador módulo M
always @(posedge clk)
  if (contadorParaDividir == M - 1) 
    contadorParaDividir <= 0;
  else 
    contadorParaDividir <= contadorParaDividir + 1;
    
//-- Sacar el bit mas significativo por clk_salida
assign clk_salida = contadorParaDividir[N-1];
    
endmodule

TPI_CajaMusicalFinal/freqdividerM/freqdividerM_tb.v
module freqdividerM_tb();
    
//-- Registro para generar la señal de reloj
reg clk_test = 0;
wire clk_salida_test;
    
//-- Probamos con 5 para que no demore mucho
freqdividerM #(5)
  UUT(
    .clk(clk_test),
    .clk_salida(clk_salida_test)
  );
    
//-- Generador de reloj
always #1 clk_test = ~clk_test;
    
//-- Proceso al inicio
initial begin
    
  //-- Fichero donde almacenar los resultados
  $dumpfile("freqdividerM_tb.vcd");
  $dumpvars(0, freqdividerM_tb);
    
  # 3000 $display("FIN de la simulacion");
  $finish;
end
endmodule

TPI_CajaMusicalFinal/freqdividerM/freqdividerM_tb.vcd
$date
	Mon Jun 17 16:12:06 2024
$end
$version
	Icarus Verilog
$end
$timescale
	1ps
$end
$scope module freqdividerM_tb $end
$var wire 1 ! clk_salida_test $end
$var reg 1 " clk_test $end
$scope module UUT $end
$var wire 1 " clk $end
$var wire 1 ! clk_salida $end
$var reg 3 # contadorParaDividir [2:0] $end
$upscope $end
$upscope $end
$enddefinitions $end
#0
$dumpvars
b0 #
0"
0!
$end
#1
b1 #
1"
#2
0"
#3
b10 #
1"
#4
0"
#5
b11 #
1"
#6
0"
#7
1!
b100 #
1"
#8
0"
#9
0!
b0 #
1"
#10
0"
#11
b1 #
1"
#12
0"
#13
b10 #
1"
#14
0"
#15
b11 #
1"
#16
0"
#17
1!
b100 #
1"
#18
0"
#19
0!
b0 #
1"
#20
0"
#21
b1 #
1"
#22
0"
#23
b10 #
1"
#24
0"
#25
b11 #
1"
#26
0"
#27
1!
b100 #
1"
#28
0"
#29
0!
b0 #
1"
#30
0"
#31
b1 #
1"
#32
0"
#33
b10 #
1"
#34
0"
#35
b11 #
1"
#36
0"
#37
1!
b100 #
1"
#38
0"
#39
0!
b0 #
1"
#40
0"
#41
b1 #
1"
#42
0"
#43
b10 #
1"
#44
0"
#45
b11 #
1"
#46
0"
#47
1!
b100 #
1"
#48
0"
#49
0!
b0 #
1"
#50
0"
#51
b1 #
1"
#52
0"
#53
b10 #
1"
#54
0"
#55
b11 #
1"
#56
0"
#57
1!
b100 #
1"
#58
0"
#59
0!
b0 #
1"
#60
0"
#61
b1 #
1"
#62
0"
#63
b10 #
1"
#64
0"
#65
b11 #
1"
#66
0"
#67
1!
b100 #
1"
#68
0"
#69
0!
b0 #
1"
#70
0"
#71
b1 #
1"
#72
0"
#73
b10 #
1"
#74
0"
#75
b11 #
1"
#76
0"
#77
1!
b100 #
1"
#78
0"
#79
0!
b0 #
1"
#80
0"
#81
b1 #
1"
#82
0"
#83
b10 #
1"
#84
0"
#85
b11 #
1"
#86
0"
#87
1!
b100 #
1"
#88
0"
#89
0!
b0 #
1"
#90
0"
#91
b1 #
1"
#92
0"
#93
b10 #
1"
#94
0"
#95
b11 #
1"
#96
0"
#97
1!
b100 #
1"
#98
0"
#99
0!
b0 #
1"
#100
0"
#101
b1 #
1"
#102
0"
#103
b10 #
1"
#104
0"
#105
b11 #
1"
#106
0"
#107
1!
b100 #
1"
#108
0"
#109
0!
b0 #
1"
#110
0"
#111
b1 #
1"
#112
0"
#113
b10 #
1"
#114
0"
#115
b11 #
1"
#116
0"
#117
1!
b100 #
1"
#118
0"
#119
0!
b0 #
1"
#120
0"
#121
b1 #
1"
#122
0"
#123
b10 #
1"
#124
0"
#125
b11 #
1"
#126
0"
#127
1!
b100 #
1"
#128
0"
#129
0!
b0 #
1"
#130
0"
#131
b1 #
1"
#132
0"
#133
b10 #
1"
#134
0"
#135
b11 #
1"
#136
0"
#137
1!
b100 #
1"
#138
0"
#139
0!
b0 #
1"
#140
0"
#141
b1 #
1"
#142
0"
#143
b10 #
1"
#144
0"
#145
b11 #
1"
#146
0"
#147
1!
b100 #
1"
#148
0"
#149
0!
b0 #
1"
#150
0"
#151
b1 #
1"
#152
0"
#153
b10 #
1"
#154
0"
#155
b11 #
1"
#156
0"
#157
1!
b100 #
1"
#158
0"
#159
0!
b0 #
1"
#160
0"
#161
b1 #
1"
#162
0"
#163
b10 #
1"
#164
0"
#165
b11 #
1"
#166
0"
#167
1!
b100 #
1"
#168
0"
#169
0!
b0 #
1"
#170
0"
#171
b1 #
1"
#172
0"
#173
b10 #
1"
#174
0"
#175
b11 #
1"
#176
0"
#177
1!
b100 #
1"
#178
0"
#179
0!
b0 #
1"
#180
0"
#181
b1 #
1"
#182
0"
#183
b10 #
1"
#184
0"
#185
b11 #
1"
#186
0"
#187
1!
b100 #
1"
#188
0"
#189
0!
b0 #
1"
#190
0"
#191
b1 #
1"
#192
0"
#193
b10 #
1"
#194
0"
#195
b11 #
1"
#196
0"
#197
1!
b100 #
1"
#198
0"
#199
0!
b0 #
1"
#200
0"
#201
b1 #
1"
#202
0"
#203
b10 #
1"
#204
0"
#205
b11 #
1"
#206
0"
#207
1!
b100 #
1"
#208
0"
#209
0!
b0 #
1"
#210
0"
#211
b1 #
1"
#212
0"
#213
b10 #
1"
#214
0"
#215
b11 #
1"
#216
0"
#217
1!
b100 #
1"
#218
0"
#219
0!
b0 #
1"
#220
0"
#221
b1 #
1"
#222
0"
#223
b10 #
1"
#224
0"
#225
b11 #
1"
#226
0"
#227
1!
b100 #
1"
#228
0"
#229
0!
b0 #
1"
#230
0"
#231
b1 #
1"
#232
0"
#233
b10 #
1"
#234
0"
#235
b11 #
1"
#236
0"
#237
1!
b100 #
1"
#238
0"
#239
0!
b0 #
1"
#240
0"
#241
b1 #
1"
#242
0"
#243
b10 #
1"
#244
0"
#245
b11 #
1"
#246
0"
#247
1!
b100 #
1"
#248
0"
#249
0!
b0 #
1"
#250
0"
#251
b1 #
1"
#252
0"
#253
b10 #
1"
#254
0"
#255
b11 #
1"
#256
0"
#257
1!
b100 #
1"
#258
0"
#259
0!
b0 #
1"
#260
0"
#261
b1 #
1"
#262
0"
#263
b10 #
1"
#264
0"
#265
b11 #
1"
#266
0"
#267
1!
b100 #
1"
#268
0"
#269
0!
b0 #
1"
#270
0"
#271
b1 #
1"
#272
0"
#273
b10 #
1"
#274
0"
#275
b11 #
1"
#276
0"
#277
1!
b100 #
1"
#278
0"
#279
0!
b0 #
1"
#280
0"
#281
b1 #
1"
#282
0"
#283
b10 #
1"
#284
0"
#285
b11 #
1"
#286
0"
#287
1!
b100 #
1"
#288
0"
#289
0!
b0 #
1"
#290
0"
#291
b1 #
1"
#292
0"
#293
b10 #
1"
#294
0"
#295
b11 #
1"
#296
0"
#297
1!
b100 #
1"
#298
0"
#299
0!
b0 #
1"
#300
0"
#301
b1 #
1"
#302
0"
#303
b10 #
1"
#304
0"
#305
b11 #
1"
#306
0"
#307
1!
b100 #
1"
#308
0"
#309
0!
b0 #
1"
#310
0"
#311
b1 #
1"
#312
0"
#313
b10 #
1"
#314
0"
#315
b11 #
1"
#316
0"
#317
1!
b100 #
1"
#318
0"
#319
0!
b0 #
1"
#320
0"
#321
b1 #
1"
#322
0"
#323
b10 #
1"
#324
0"
#325
b11 #
1"
#326
0"
#327
1!
b100 #
1"
#328
0"
#329
0!
b0 #
1"
#330
0"
#331
b1 #
1"
#332
0"
#333
b10 #
1"
#334
0"
#335
b11 #
1"
#336
0"
#337
1!
b100 #
1"
#338
0"
#339
0!
b0 #
1"
#340
0"
#341
b1 #
1"
#342
0"
#343
b10 #
1"
#344
0"
#345
b11 #
1"
#346
0"
#347
1!
b100 #
1"
#348
0"
#349
0!
b0 #
1"
#350
0"
#351
b1 #
1"
#352
0"
#353
b10 #
1"
#354
0"
#355
b11 #
1"
#356
0"
#357
1!
b100 #
1"
#358
0"
#359
0!
b0 #
1"
#360
0"
#361
b1 #
1"
#362
0"
#363
b10 #
1"
#364
0"
#365
b11 #
1"
#366
0"
#367
1!
b100 #
1"
#368
0"
#369
0!
b0 #
1"
#370
0"
#371
b1 #
1"
#372
0"
#373
b10 #
1"
#374
0"
#375
b11 #
1"
#376
0"
#377
1!
b100 #
1"
#378
0"
#379
0!
b0 #
1"
#380
0"
#381
b1 #
1"
#382
0"
#383
b10 #
1"
#384
0"
#385
b11 #
1"
#386
0"
#387
1!
b100 #
1"
#388
0"
#389
0!
b0 #
1"
#390
0"
#391
b1 #
1"
#392
0"
#393
b10 #
1"
#394
0"
#395
b11 #
1"
#396
0"
#397
1!
b100 #
1"
#398
0"
#399
0!
b0 #
1"
#400
0"
#401
b1 #
1"
#402
0"
#403
b10 #
1"
#404
0"
#405
b11 #
1"
#406
0"
#407
1!
b100 #
1"
#408
0"
#409
0!
b0 #
1"
#410
0"
#411
b1 #
1"
#412
0"
#413
b10 #
1"
#414
0"
#415
b11 #
1"
#416
0"
#417
1!
b100 #
1"
#418
0"
#419
0!
b0 #
1"
#420
0"
#421
b1 #
1"
#422
0"
#423
b10 #
1"
#424
0"
#425
b11 #
1"
#426
0"
#427
1!
b100 #
1"
#428
0"
#429
0!
b0 #
1"
#430
0"
#431
b1 #
1"
#432
0"
#433
b10 #
1"
#434
0"
#435
b11 #
1"
#436
0"
#437
1!
b100 #
1"
#438
0"
#439
0!
b0 #
1"
#440
0"
#441
b1 #
1"
#442
0"
#443
b10 #
1"
#444
0"
#445
b11 #
1"
#446
0"
#447
1!
b100 #
1"
#448
0"
#449
0!
b0 #
1"
#450
0"
#451
b1 #
1"
#452
0"
#453
b10 #
1"
#454
0"
#455
b11 #
1"
#456
0"
#457
1!
b100 #
1"
#458
0"
#459
0!
b0 #
1"
#460
0"
#461
b1 #
1"
#462
0"
#463
b10 #
1"
#464
0"
#465
b11 #
1"
#466
0"
#467
1!
b100 #
1"
#468
0"
#469
0!
b0 #
1"
#470
0"
#471
b1 #
1"
#472
0"
#473
b10 #
1"
#474
0"
#475
b11 #
1"
#476
0"
#477
1!
b100 #
1"
#478
0"
#479
0!
b0 #
1"
#480
0"
#481
b1 #
1"
#482
0"
#483
b10 #
1"
#484
0"
#485
b11 #
1"
#486
0"
#487
1!
b100 #
1"
#488
0"
#489
0!
b0 #
1"
#490
0"
#491
b1 #
1"
#492
0"
#493
b10 #
1"
#494
0"
#495
b11 #
1"
#496
0"
#497
1!
b100 #
1"
#498
0"
#499
0!
b0 #
1"
#500
0"
#501
b1 #
1"
#502
0"
#503
b10 #
1"
#504
0"
#505
b11 #
1"
#506
0"
#507
1!
b100 #
1"
#508
0"
#509
0!
b0 #
1"
#510
0"
#511
b1 #
1"
#512
0"
#513
b10 #
1"
#514
0"
#515
b11 #
1"
#516
0"
#517
1!
b100 #
1"
#518
0"
#519
0!
b0 #
1"
#520
0"
#521
b1 #
1"
#522
0"
#523
b10 #
1"
#524
0"
#525
b11 #
1"
#526
0"
#527
1!
b100 #
1"
#528
0"
#529
0!
b0 #
1"
#530
0"
#531
b1 #
1"
#532
0"
#533
b10 #
1"
#534
0"
#535
b11 #
1"
#536
0"
#537
1!
b100 #
1"
#538
0"
#539
0!
b0 #
1"
#540
0"
#541
b1 #
1"
#542
0"
#543
b10 #
1"
#544
0"
#545
b11 #
1"
#546
0"
#547
1!
b100 #
1"
#548
0"
#549
0!
b0 #
1"
#550
0"
#551
b1 #
1"
#552
0"
#553
b10 #
1"
#554
0"
#555
b11 #
1"
#556
0"
#557
1!
b100 #
1"
#558
0"
#559
0!
b0 #
1"
#560
0"
#561
b1 #
1"
#562
0"
#563
b10 #
1"
#564
0"
#565
b11 #
1"
#566
0"
#567
1!
b100 #
1"
#568
0"
#569
0!
b0 #
1"
#570
0"
#571
b1 #
1"
#572
0"
#573
b10 #
1"
#574
0"
#575
b11 #
1"
#576
0"
#577
1!
b100 #
1"
#578
0"
#579
0!
b0 #
1"
#580
0"
#581
b1 #
1"
#582
0"
#583
b10 #
1"
#584
0"
#585
b11 #
1"
#586
0"
#587
1!
b100 #
1"
#588
0"
#589
0!
b0 #
1"
#590
0"
#591
b1 #
1"
#592
0"
#593
b10 #
1"
#594
0"
#595
b11 #
1"
#596
0"
#597
1!
b100 #
1"
#598
0"
#599
0!
b0 #
1"
#600
0"
#601
b1 #
1"
#602
0"
#603
b10 #
1"
#604
0"
#605
b11 #
1"
#606
0"
#607
1!
b100 #
1"
#608
0"
#609
0!
b0 #
1"
#610
0"
#611
b1 #
1"
#612
0"
#613
b10 #
1"
#614
0"
#615
b11 #
1"
#616
0"
#617
1!
b100 #
1"
#618
0"
#619
0!
b0 #
1"
#620
0"
#621
b1 #
1"
#622
0"
#623
b10 #
1"
#624
0"
#625
b11 #
1"
#626
0"
#627
1!
b100 #
1"
#628
0"
#629
0!
b0 #
1"
#630
0"
#631
b1 #
1"
#632
0"
#633
b10 #
1"
#634
0"
#635
b11 #
1"
#636
0"
#637
1!
b100 #
1"
#638
0"
#639
0!
b0 #
1"
#640
0"
#641
b1 #
1"
#642
0"
#643
b10 #
1"
#644
0"
#645
b11 #
1"
#646
0"
#647
1!
b100 #
1"
#648
0"
#649
0!
b0 #
1"
#650
0"
#651
b1 #
1"
#652
0"
#653
b10 #
1"
#654
0"
#655
b11 #
1"
#656
0"
#657
1!
b100 #
1"
#658
0"
#659
0!
b0 #
1"
#660
0"
#661
b1 #
1"
#662
0"
#663
b10 #
1"
#664
0"
#665
b11 #
1"
#666
0"
#667
1!
b100 #
1"
#668
0"
#669
0!
b0 #
1"
#670
0"
#671
b1 #
1"
#672
0"
#673
b10 #
1"
#674
0"
#675
b11 #
1"
#676
0"
#677
1!
b100 #
1"
#678
0"
#679
0!
b0 #
1"
#680
0"
#681
b1 #
1"
#682
0"
#683
b10 #
1"
#684
0"
#685
b11 #
1"
#686
0"
#687
1!
b100 #
1"
#688
0"
#689
0!
b0 #
1"
#690
0"
#691
b1 #
1"
#692
0"
#693
b10 #
1"
#694
0"
#695
b11 #
1"
#696
0"
#697
1!
b100 #
1"
#698
0"
#699
0!
b0 #
1"
#700
0"
#701
b1 #
1"
#702
0"
#703
b10 #
1"
#704
0"
#705
b11 #
1"
#706
0"
#707
1!
b100 #
1"
#708
0"
#709
0!
b0 #
1"
#710
0"
#711
b1 #
1"
#712
0"
#713
b10 #
1"
#714
0"
#715
b11 #
1"
#716
0"
#717
1!
b100 #
1"
#718
0"
#719
0!
b0 #
1"
#720
0"
#721
b1 #
1"
#722
0"
#723
b10 #
1"
#724
0"
#725
b11 #
1"
#726
0"
#727
1!
b100 #
1"
#728
0"
#729
0!
b0 #
1"
#730
0"
#731
b1 #
1"
#732
0"
#733
b10 #
1"
#734
0"
#735
b11 #
1"
#736
0"
#737
1!
b100 #
1"
#738
0"
#739
0!
b0 #
1"
#740
0"
#741
b1 #
1"
#742
0"
#743
b10 #
1"
#744
0"
#745
b11 #
1"
#746
0"
#747
1!
b100 #
1"
#748
0"
#749
0!
b0 #
1"
#750
0"
#751
b1 #
1"
#752
0"
#753
b10 #
1"
#754
0"
#755
b11 #
1"
#756
0"
#757
1!
b100 #
1"
#758
0"
#759
0!
b0 #
1"
#760
0"
#761
b1 #
1"
#762
0"
#763
b10 #
1"
#764
0"
#765
b11 #
1"
#766
0"
#767
1!
b100 #
1"
#768
0"
#769
0!
b0 #
1"
#770
0"
#771
b1 #
1"
#772
0"
#773
b10 #
1"
#774
0"
#775
b11 #
1"
#776
0"
#777
1!
b100 #
1"
#778
0"
#779
0!
b0 #
1"
#780
0"
#781
b1 #
1"
#782
0"
#783
b10 #
1"
#784
0"
#785
b11 #
1"
#786
0"
#787
1!
b100 #
1"
#788
0"
#789
0!
b0 #
1"
#790
0"
#791
b1 #
1"
#792
0"
#793
b10 #
1"
#794
0"
#795
b11 #
1"
#796
0"
#797
1!
b100 #
1"
#798
0"
#799
0!
b0 #
1"
#800
0"
#801
b1 #
1"
#802
0"
#803
b10 #
1"
#804
0"
#805
b11 #
1"
#806
0"
#807
1!
b100 #
1"
#808
0"
#809
0!
b0 #
1"
#810
0"
#811
b1 #
1"
#812
0"
#813
b10 #
1"
#814
0"
#815
b11 #
1"
#816
0"
#817
1!
b100 #
1"
#818
0"
#819
0!
b0 #
1"
#820
0"
#821
b1 #
1"
#822
0"
#823
b10 #
1"
#824
0"
#825
b11 #
1"
#826
0"
#827
1!
b100 #
1"
#828
0"
#829
0!
b0 #
1"
#830
0"
#831
b1 #
1"
#832
0"
#833
b10 #
1"
#834
0"
#835
b11 #
1"
#836
0"
#837
1!
b100 #
1"
#838
0"
#839
0!
b0 #
1"
#840
0"
#841
b1 #
1"
#842
0"
#843
b10 #
1"
#844
0"
#845
b11 #
1"
#846
0"
#847
1!
b100 #
1"
#848
0"
#849
0!
b0 #
1"
#850
0"
#851
b1 #
1"
#852
0"
#853
b10 #
1"
#854
0"
#855
b11 #
1"
#856
0"
#857
1!
b100 #
1"
#858
0"
#859
0!
b0 #
1"
#860
0"
#861
b1 #
1"
#862
0"
#863
b10 #
1"
#864
0"
#865
b11 #
1"
#866
0"
#867
1!
b100 #
1"
#868
0"
#869
0!
b0 #
1"
#870
0"
#871
b1 #
1"
#872
0"
#873
b10 #
1"
#874
0"
#875
b11 #
1"
#876
0"
#877
1!
b100 #
1"
#878
0"
#879
0!
b0 #
1"
#880
0"
#881
b1 #
1"
#882
0"
#883
b10 #
1"
#884
0"
#885
b11 #
1"
#886
0"
#887
1!
b100 #
1"
#888
0"
#889
0!
b0 #
1"
#890
0"
#891
b1 #
1"
#892
0"
#893
b10 #
1"
#894
0"
#895
b11 #
1"
#896
0"
#897
1!
b100 #
1"
#898
0"
#899
0!
b0 #
1"
#900
0"
#901
b1 #
1"
#902
0"
#903
b10 #
1"
#904
0"
#905
b11 #
1"
#906
0"
#907
1!
b100 #
1"
#908
0"
#909
0!
b0 #
1"
#910
0"
#911
b1 #
1"
#912
0"
#913
b10 #
1"
#914
0"
#915
b11 #
1"
#916
0"
#917
1!
b100 #
1"
#918
0"
#919
0!
b0 #
1"
#920
0"
#921
b1 #
1"
#922
0"
#923
b10 #
1"
#924
0"
#925
b11 #
1"
#926
0"
#927
1!
b100 #
1"
#928
0"
#929
0!
b0 #
1"
#930
0"
#931
b1 #
1"
#932
0"
#933
b10 #
1"
#934
0"
#935
b11 #
1"
#936
0"
#937
1!
b100 #
1"
#938
0"
#939
0!
b0 #
1"
#940
0"
#941
b1 #
1"
#942
0"
#943
b10 #
1"
#944
0"
#945
b11 #
1"
#946
0"
#947
1!
b100 #
1"
#948
0"
#949
0!
b0 #
1"
#950
0"
#951
b1 #
1"
#952
0"
#953
b10 #
1"
#954
0"
#955
b11 #
1"
#956
0"
#957
1!
b100 #
1"
#958
0"
#959
0!
b0 #
1"
#960
0"
#961
b1 #
1"
#962
0"
#963
b10 #
1"
#964
0"
#965
b11 #
1"
#966
0"
#967
1!
b100 #
1"
#968
0"
#969
0!
b0 #
1"
#970
0"
#971
b1 #
1"
#972
0"
#973
b10 #
1"
#974
0"
#975
b11 #
1"
#976
0"
#977
1!
b100 #
1"
#978
0"
#979
0!
b0 #
1"
#980
0"
#981
b1 #
1"
#982
0"
#983
b10 #
1"
#984
0"
#985
b11 #
1"
#986
0"
#987
1!
b100 #
1"
#988
0"
#989
0!
b0 #
1"
#990
0"
#991
b1 #
1"
#992
0"
#993
b10 #
1"
#994
0"
#995
b11 #
1"
#996
0"
#997
1!
b100 #
1"
#998
0"
#999
0!
b0 #
1"
#1000
0"
#1001
b1 #
1"
#1002
0"
#1003
b10 #
1"
#1004
0"
#1005
b11 #
1"
#1006
0"
#1007
1!
b100 #
1"
#1008
0"
#1009
0!
b0 #
1"
#1010
0"
#1011
b1 #
1"
#1012
0"
#1013
b10 #
1"
#1014
0"
#1015
b11 #
1"
#1016
0"
#1017
1!
b100 #
1"
#1018
0"
#1019
0!
b0 #
1"
#1020
0"
#1021
b1 #
1"
#1022
0"
#1023
b10 #
1"
#1024
0"
#1025
b11 #
1"
#1026
0"
#1027
1!
b100 #
1"
#1028
0"
#1029
0!
b0 #
1"
#1030
0"
#1031
b1 #
1"
#1032
0"
#1033
b10 #
1"
#1034
0"
#1035
b11 #
1"
#1036
0"
#1037
1!
b100 #
1"
#1038
0"
#1039
0!
b0 #
1"
#1040
0"
#1041
b1 #
1"
#1042
0"
#1043
b10 #
1"
#1044
0"
#1045
b11 #
1"
#1046
0"
#1047
1!
b100 #
1"
#1048
0"
#1049
0!
b0 #
1"
#1050
0"
#1051
b1 #
1"
#1052
0"
#1053
b10 #
1"
#1054
0"
#1055
b11 #
1"
#1056
0"
#1057
1!
b100 #
1"
#1058
0"
#1059
0!
b0 #
1"
#1060
0"
#1061
b1 #
1"
#1062
0"
#1063
b10 #
1"
#1064
0"
#1065
b11 #
1"
#1066
0"
#1067
1!
b100 #
1"
#1068
0"
#1069
0!
b0 #
1"
#1070
0"
#1071
b1 #
1"
#1072
0"
#1073
b10 #
1"
#1074
0"
#1075
b11 #
1"
#1076
0"
#1077
1!
b100 #
1"
#1078
0"
#1079
0!
b0 #
1"
#1080
0"
#1081
b1 #
1"
#1082
0"
#1083
b10 #
1"
#1084
0"
#1085
b11 #
1"
#1086
0"
#1087
1!
b100 #
1"
#1088
0"
#1089
0!
b0 #
1"
#1090
0"
#1091
b1 #
1"
#1092
0"
#1093
b10 #
1"
#1094
0"
#1095
b11 #
1"
#1096
0"
#1097
1!
b100 #
1"
#1098
0"
#1099
0!
b0 #
1"
#1100
0"
#1101
b1 #
1"
#1102
0"
#1103
b10 #
1"
#1104
0"
#1105
b11 #
1"
#1106
0"
#1107
1!
b100 #
1"
#1108
0"
#1109
0!
b0 #
1"
#1110
0"
#1111
b1 #
1"
#1112
0"
#1113
b10 #
1"
#1114
0"
#1115
b11 #
1"
#1116
0"
#1117
1!
b100 #
1"
#1118
0"
#1119
0!
b0 #
1"
#1120
0"
#1121
b1 #
1"
#1122
0"
#1123
b10 #
1"
#1124
0"
#1125
b11 #
1"
#1126
0"
#1127
1!
b100 #
1"
#1128
0"
#1129
0!
b0 #
1"
#1130
0"
#1131
b1 #
1"
#1132
0"
#1133
b10 #
1"
#1134
0"
#1135
b11 #
1"
#1136
0"
#1137
1!
b100 #
1"
#1138
0"
#1139
0!
b0 #
1"
#1140
0"
#1141
b1 #
1"
#1142
0"
#1143
b10 #
1"
#1144
0"
#1145
b11 #
1"
#1146
0"
#1147
1!
b100 #
1"
#1148
0"
#1149
0!
b0 #
1"
#1150
0"
#1151
b1 #
1"
#1152
0"
#1153
b10 #
1"
#1154
0"
#1155
b11 #
1"
#1156
0"
#1157
1!
b100 #
1"
#1158
0"
#1159
0!
b0 #
1"
#1160
0"
#1161
b1 #
1"
#1162
0"
#1163
b10 #
1"
#1164
0"
#1165
b11 #
1"
#1166
0"
#1167
1!
b100 #
1"
#1168
0"
#1169
0!
b0 #
1"
#1170
0"
#1171
b1 #
1"
#1172
0"
#1173
b10 #
1"
#1174
0"
#1175
b11 #
1"
#1176
0"
#1177
1!
b100 #
1"
#1178
0"
#1179
0!
b0 #
1"
#1180
0"
#1181
b1 #
1"
#1182
0"
#1183
b10 #
1"
#1184
0"
#1185
b11 #
1"
#1186
0"
#1187
1!
b100 #
1"
#1188
0"
#1189
0!
b0 #
1"
#1190
0"
#1191
b1 #
1"
#1192
0"
#1193
b10 #
1"
#1194
0"
#1195
b11 #
1"
#1196
0"
#1197
1!
b100 #
1"
#1198
0"
#1199
0!
b0 #
1"
#1200
0"
#1201
b1 #
1"
#1202
0"
#1203
b10 #
1"
#1204
0"
#1205
b11 #
1"
#1206
0"
#1207
1!
b100 #
1"
#1208
0"
#1209
0!
b0 #
1"
#1210
0"
#1211
b1 #
1"
#1212
0"
#1213
b10 #
1"
#1214
0"
#1215
b11 #
1"
#1216
0"
#1217
1!
b100 #
1"
#1218
0"
#1219
0!
b0 #
1"
#1220
0"
#1221
b1 #
1"
#1222
0"
#1223
b10 #
1"
#1224
0"
#1225
b11 #
1"
#1226
0"
#1227
1!
b100 #
1"
#1228
0"
#1229
0!
b0 #
1"
#1230
0"
#1231
b1 #
1"
#1232
0"
#1233
b10 #
1"
#1234
0"
#1235
b11 #
1"
#1236
0"
#1237
1!
b100 #
1"
#1238
0"
#1239
0!
b0 #
1"
#1240
0"
#1241
b1 #
1"
#1242
0"
#1243
b10 #
1"
#1244
0"
#1245
b11 #
1"
#1246
0"
#1247
1!
b100 #
1"
#1248
0"
#1249
0!
b0 #
1"
#1250
0"
#1251
b1 #
1"
#1252
0"
#1253
b10 #
1"
#1254
0"
#1255
b11 #
1"
#1256
0"
#1257
1!
b100 #
1"
#1258
0"
#1259
0!
b0 #
1"
#1260
0"
#1261
b1 #
1"
#1262
0"
#1263
b10 #
1"
#1264
0"
#1265
b11 #
1"
#1266
0"
#1267
1!
b100 #
1"
#1268
0"
#1269
0!
b0 #
1"
#1270
0"
#1271
b1 #
1"
#1272
0"
#1273
b10 #
1"
#1274
0"
#1275
b11 #
1"
#1276
0"
#1277
1!
b100 #
1"
#1278
0"
#1279
0!
b0 #
1"
#1280
0"
#1281
b1 #
1"
#1282
0"
#1283
b10 #
1"
#1284
0"
#1285
b11 #
1"
#1286
0"
#1287
1!
b100 #
1"
#1288
0"
#1289
0!
b0 #
1"
#1290
0"
#1291
b1 #
1"
#1292
0"
#1293
b10 #
1"
#1294
0"
#1295
b11 #
1"
#1296
0"
#1297
1!
b100 #
1"
#1298
0"
#1299
0!
b0 #
1"
#1300
0"
#1301
b1 #
1"
#1302
0"
#1303
b10 #
1"
#1304
0"
#1305
b11 #
1"
#1306
0"
#1307
1!
b100 #
1"
#1308
0"
#1309
0!
b0 #
1"
#1310
0"
#1311
b1 #
1"
#1312
0"
#1313
b10 #
1"
#1314
0"
#1315
b11 #
1"
#1316
0"
#1317
1!
b100 #
1"
#1318
0"
#1319
0!
b0 #
1"
#1320
0"
#1321
b1 #
1"
#1322
0"
#1323
b10 #
1"
#1324
0"
#1325
b11 #
1"
#1326
0"
#1327
1!
b100 #
1"
#1328
0"
#1329
0!
b0 #
1"
#1330
0"
#1331
b1 #
1"
#1332
0"
#1333
b10 #
1"
#1334
0"
#1335
b11 #
1"
#1336
0"
#1337
1!
b100 #
1"
#1338
0"
#1339
0!
b0 #
1"
#1340
0"
#1341
b1 #
1"
#1342
0"
#1343
b10 #
1"
#1344
0"
#1345
b11 #
1"
#1346
0"
#1347
1!
b100 #
1"
#1348
0"
#1349
0!
b0 #
1"
#1350
0"
#1351
b1 #
1"
#1352
0"
#1353
b10 #
1"
#1354
0"
#1355
b11 #
1"
#1356
0"
#1357
1!
b100 #
1"
#1358
0"
#1359
0!
b0 #
1"
#1360
0"
#1361
b1 #
1"
#1362
0"
#1363
b10 #
1"
#1364
0"
#1365
b11 #
1"
#1366
0"
#1367
1!
b100 #
1"
#1368
0"
#1369
0!
b0 #
1"
#1370
0"
#1371
b1 #
1"
#1372
0"
#1373
b10 #
1"
#1374
0"
#1375
b11 #
1"
#1376
0"
#1377
1!
b100 #
1"
#1378
0"
#1379
0!
b0 #
1"
#1380
0"
#1381
b1 #
1"
#1382
0"
#1383
b10 #
1"
#1384
0"
#1385
b11 #
1"
#1386
0"
#1387
1!
b100 #
1"
#1388
0"
#1389
0!
b0 #
1"
#1390
0"
#1391
b1 #
1"
#1392
0"
#1393
b10 #
1"
#1394
0"
#1395
b11 #
1"
#1396
0"
#1397
1!
b100 #
1"
#1398
0"
#1399
0!
b0 #
1"
#1400
0"
#1401
b1 #
1"
#1402
0"
#1403
b10 #
1"
#1404
0"
#1405
b11 #
1"
#1406
0"
#1407
1!
b100 #
1"
#1408
0"
#1409
0!
b0 #
1"
#1410
0"
#1411
b1 #
1"
#1412
0"
#1413
b10 #
1"
#1414
0"
#1415
b11 #
1"
#1416
0"
#1417
1!
b100 #
1"
#1418
0"
#1419
0!
b0 #
1"
#1420
0"
#1421
b1 #
1"
#1422
0"
#1423
b10 #
1"
#1424
0"
#1425
b11 #
1"
#1426
0"
#1427
1!
b100 #
1"
#1428
0"
#1429
0!
b0 #
1"
#1430
0"
#1431
b1 #
1"
#1432
0"
#1433
b10 #
1"
#1434
0"
#1435
b11 #
1"
#1436
0"
#1437
1!
b100 #
1"
#1438
0"
#1439
0!
b0 #
1"
#1440
0"
#1441
b1 #
1"
#1442
0"
#1443
b10 #
1"
#1444
0"
#1445
b11 #
1"
#1446
0"
#1447
1!
b100 #
1"
#1448
0"
#1449
0!
b0 #
1"
#1450
0"
#1451
b1 #
1"
#1452
0"
#1453
b10 #
1"
#1454
0"
#1455
b11 #
1"
#1456
0"
#1457
1!
b100 #
1"
#1458
0"
#1459
0!
b0 #
1"
#1460
0"
#1461
b1 #
1"
#1462
0"
#1463
b10 #
1"
#1464
0"
#1465
b11 #
1"
#1466
0"
#1467
1!
b100 #
1"
#1468
0"
#1469
0!
b0 #
1"
#1470
0"
#1471
b1 #
1"
#1472
0"
#1473
b10 #
1"
#1474
0"
#1475
b11 #
1"
#1476
0"
#1477
1!
b100 #
1"
#1478
0"
#1479
0!
b0 #
1"
#1480
0"
#1481
b1 #
1"
#1482
0"
#1483
b10 #
1"
#1484
0"
#1485
b11 #
1"
#1486
0"
#1487
1!
b100 #
1"
#1488
0"
