ej9_gtp2/simpKarnaugh.v
module simpKarnaugh (
    //Refers Guido's example upload to e-fich
    input wire A3, A2, A1, A0,
    output wire Z
);

//Internal variables declaration

//Body
assign Z = (~A3 & ~A1 & ~A0) | (~A3 & A2 & ~A1) | (~A3 & A2 & ~A0) | (~A3 & ~A2 & A1 & A0);
    
endmodule

gtp2_ej9/simpKarnaugh_tb.v
//-------------------------------------------------------------------
//-- simpKarnaugh_tb.v
//-- Testbench
//-------------------------------------------------------------------
//-- Eberhardt Maximiliano
//-- GPL license
//-------------------------------------------------------------------

`default_nettype none
`define DUMPSTR(x) `"x.vcd`"
`timescale 100 ns / 10 ns
// timescale <time_unit> / <time_precision>

module simpKarnaugh_tb();

//-- Simulation time: 1us (10 * 100ns)
parameter DURATION = 10;

//-- Clock signal. It is not used in this simulation
reg clk = 0;
always #0.5 clk = ~clk;

// simpKarnaugh ports
reg A0_test, A1_test, A2_test, A3_test;
wire z_test;

simpKarnaugh UUT(
    .A0(A0_test),
    .A1(A1_test),
    .A2(A2_test),
    .A3(A3_test),
    .Z(z_test)
);

integer i;

initial begin

    //-- File were to store the simulation results
    $dumpfile(`DUMPSTR(`VCD_OUTPUT));
    $dumpvars(0, simpKarnaugh_tb);

    for (i=0; i<16; i=i+1)
    begin
        $display ("Current loop # %0d", i); //Esto "Reinicia" el loop de los datos de prueba
        $display ("Current loop # %0b", i); //Esto "Reinicia" el loop de los datos de prueba

        //Primera prueba
        A3_test = 0;
        A2_test = 1;
        A1_test = 1;
        A0_test = 0;
        #2;

        //Segunda prueba
        A3_test = 1;
        A2_test = 0;
        A1_test = 0;
        A0_test = 1;
        #2;
    end

    #(DURATION) $display("End of simulation");
    $finish;
end

endmodule

ej9_gtp2/simpKarnaugh_tb.vcd
$date
	Sun May  5 17:43:28 2024
$end
$version
	Icarus Verilog
$end
$timescale
	1ps
$end
$scope module simpKarnaugh_tb $end
$var wire 1 ! z_test $end
$var reg 1 " A0_test $end
$var reg 1 # A1_test $end
$var reg 1 $ A2_test $end
$var reg 1 % A3_test $end
$var reg 1 & clk $end
$var integer 32 ' i [31:0] $end
$scope module UUT $end
$var wire 1 " A0 $end
$var wire 1 # A1 $end
$var wire 1 $ A2 $end
$var wire 1 % A3 $end
$var wire 1 ! Z $end
$upscope $end
$upscope $end
$enddefinitions $end
#0
$dumpvars
b0 '
0&
0%
1$
1#
0"
1!
$end
#50000
1&
#100000
0&
#150000
1&
#200000
0!
0&
1"
0#
0$
1%
#250000
1&
#300000
0&
#350000
1&
#400000
1!
0&
0"
1#
1$
0%
b1 '
#450000
1&
#500000
0&
#550000
1&
#600000
0!
0&
1"
0#
0$
1%
#650000
1&
#700000
0&
#750000
1&
#800000
1!
0&
0"
1#
1$
0%
b10 '
#850000
1&
#900000
0&
#950000
1&
#1000000
0!
0&
1"
0#
0$
1%
#1050000
1&
#1100000
0&
#1150000
1&
#1200000
1!
0&
0"
1#
1$
0%
b11 '
#1250000
1&
#1300000
0&
#1350000
1&
#1400000
0!
0&
1"
0#
0$
1%
#1450000
1&
#1500000
0&
#1550000
1&
#1600000
1!
0&
0"
1#
1$
0%
b100 '
#1650000
1&
#1700000
0&
#1750000
1&
#1800000
0!
0&
1"
0#
0$
1%
#1850000
1&
#1900000
0&
#1950000
1&
#2000000
1!
0&
0"
1#
1$
0%
b101 '
#2050000
1&
#2100000
0&
#2150000
1&
#2200000
0!
0&
1"
0#
0$
1%
#2250000
1&
#2300000
0&
#2350000
1&
#2400000
1!
0&
0"
1#
1$
0%
b110 '
#2450000
1&
#2500000
0&
#2550000
1&
#2600000
0!
0&
1"
0#
0$
1%
#2650000
1&
#2700000
0&
#2750000
1&
#2800000
1!
0&
0"
1#
1$
0%
b111 '
#2850000
1&
#2900000
0&
#2950000
1&
#3000000
0!
0&
1"
0#
0$
1%
#3050000
1&
#3100000
0&
#3150000
1&
#3200000
1!
0&
0"
1#
1$
0%
b1000 '
#3250000
1&
#3300000
0&
#3350000
1&
#3400000
0!
0&
1"
0#
0$
1%
#3450000
1&
#3500000
0&
#3550000
1&
#3600000
1!
0&
0"
1#
1$
0%
b1001 '
#3650000
1&
#3700000
0&
#3750000
1&
#3800000
0!
0&
1"
0#
0$
1%
#3850000
1&
#3900000
0&
#3950000
1&
#4000000
1!
0&
0"
1#
1$
0%
b1010 '
#4050000
1&
#4100000
0&
#4150000
1&
#4200000
0!
0&
1"
0#
0$
1%
#4250000
1&
#4300000
0&
#4350000
1&
#4400000
1!
0&
0"
1#
1$
0%
b1011 '
#4450000
1&
#4500000
0&
#4550000
1&
#4600000
0!
0&
1"
0#
0$
1%
#4650000
1&
#4700000
0&
#4750000
1&
#4800000
1!
0&
0"
1#
1$
0%
b1100 '
#4850000
1&
#4900000
0&
#4950000
1&
#5000000
0!
0&
1"
0#
0$
1%
#5050000
1&
#5100000
0&
#5150000
1&
#5200000
1!
0&
0"
1#
1$
0%
b1101 '
#5250000
1&
#5300000
0&
#5350000
1&
#5400000
0!
0&
1"
0#
0$
1%
#5450000
1&
#5500000
0&
#5550000
1&
#5600000
1!
0&
0"
1#
1$
0%
b1110 '
#5650000
1&
#5700000
0&
#5750000
1&
#5800000
0!
0&
1"
0#
0$
1%
#5850000
1&
#5900000
0&
#5950000
1&
#6000000
1!
0&
0"
1#
1$
0%
b1111 '
#6050000
1&
#6100000
0&
#6150000
1&
#6200000
0!
0&
1"
0#
0$
1%
#6250000
1&
#6300000
0&
#6350000
1&
#6400000
0&
b10000 '
